qcall/__init__.py
qcall/qcall.py
qcall-0.1.2.dist-info/LICENSE
qcall-0.1.2.dist-info/METADATA
qcall-0.1.2.dist-info/NOTICE
qcall-0.1.2.dist-info/WHEEL
qcall-0.1.2.dist-info/top_level.txt
qcall-0.1.2.dist-info/RECORD
