Metadata-Version: 2.1
Name: qcall
Version: 0.1.2
Summary: A module for dynamically calling Python functions
Home-page: https://github.com/andmeln/qcall/
Author: Andrey Melnikov
Author-email: andmeln@hotmail.com
License: Apache License, Version 2.0
Requires-Python: >=3.7
License-File: LICENSE
License-File: NOTICE
